fastentry/__init__.py
fastentry/cli.py
fastentry/core.py
fastentry/generator.py
fastentry/main_completion.py
fastentry-0.2.2.dist-info/licenses/LICENSE
fastentry-0.2.2.dist-info/METADATA
fastentry-0.2.2.dist-info/WHEEL
fastentry-0.2.2.dist-info/entry_points.txt
fastentry-0.2.2.dist-info/top_level.txt
fastentry-0.2.2.dist-info/RECORD
