Metadata-Version: 2.4
Name: fastentry
Version: 0.2.2
Summary: Accelerate Python CLI tab completion with automatic snapshot-based entrypoint generation
Author-email: FastEntry Contributors <fastentry@example.com>
License: MIT
Project-URL: Homepage, https://github.com/example/fastentry
Project-URL: Repository, https://github.com/example/fastentry
Project-URL: Issues, https://github.com/example/fastentry/issues
Classifier: Development Status :: 3 - Alpha
Classifier: Intended Audience :: Developers
Classifier: License :: OSI Approved :: MIT License
Classifier: Programming Language :: Python :: 3
Classifier: Programming Language :: Python :: 3.8
Classifier: Programming Language :: Python :: 3.9
Classifier: Programming Language :: Python :: 3.10
Classifier: Programming Language :: Python :: 3.11
Classifier: Topic :: Software Development :: Libraries :: Python Modules
Classifier: Topic :: System :: Shells
Requires-Python: >=3.8
License-File: LICENSE
Requires-Dist: argcomplete>=3.0.0
Requires-Dist: argparse
Provides-Extra: dev
Requires-Dist: pytest>=7.0.0; extra == "dev"
Requires-Dist: black>=22.0.0; extra == "dev"
Requires-Dist: flake8>=5.0.0; extra == "dev"
Dynamic: license-file
